MANIFEST.in
README.txt
setup.py
collective/__init__.py
collective.js.prettify.egg-info/PKG-INFO
collective.js.prettify.egg-info/SOURCES.txt
collective.js.prettify.egg-info/dependency_links.txt
collective.js.prettify.egg-info/entry_points.txt
collective.js.prettify.egg-info/namespace_packages.txt
collective.js.prettify.egg-info/not-zip-safe
collective.js.prettify.egg-info/requires.txt
collective.js.prettify.egg-info/top_level.txt
collective/js/__init__.py
collective/js/prettify/__init__.py
collective/js/prettify/configure.zcml
collective/js/prettify/interfaces.py
collective/js/prettify/tests.py
collective/js/prettify/version.txt
collective/js/prettify/javascripts/lang-apollo.js
collective/js/prettify/javascripts/lang-css.js
collective/js/prettify/javascripts/lang-hs.js
collective/js/prettify/javascripts/lang-lisp.js
collective/js/prettify/javascripts/lang-lua.js
collective/js/prettify/javascripts/lang-ml.js
collective/js/prettify/javascripts/lang-proto.js
collective/js/prettify/javascripts/lang-scala.js
collective/js/prettify/javascripts/lang-sql.js
collective/js/prettify/javascripts/lang-vb.js
collective/js/prettify/javascripts/lang-vhdl.js
collective/js/prettify/javascripts/lang-wiki.js
collective/js/prettify/javascripts/lang-yaml.js
collective/js/prettify/javascripts/prettify.js
collective/js/prettify/javascripts/prettyprint.js
collective/js/prettify/profiles/default/browserlayers.xml
collective/js/prettify/profiles/default/cssregistry.xml
collective/js/prettify/profiles/default/jsregistry.xml
collective/js/prettify/profiles/default/metadata.xml
collective/js/prettify/profiles/default/tinymce.xml
collective/js/prettify/stylesheets/prettify.css
docs/HISTORY.txt
docs/INSTALL.txt
docs/LICENSE.GPL
docs/LICENSE.txt