Metadata-Version: 1.0
Name: collective.js.prettify
Version: 0.2
Summary: Javascript code prettifier for Plone
Home-page: http://plone.org/products/collective.js.prettify
Author: Simone Orsi
Author-email: simahawk@gmail.com
License: GPL
Keywords: Plone JQuery Javascript Prettify Code highlighter
Platform: UNKNOWN
Classifier: Framework :: Plone
Classifier: Intended Audience :: Developers
Classifier: Intended Audience :: End Users/Desktop
Classifier: Topic :: Software Development :: Libraries :: Python Modules
Classifier: License :: OSI Approved :: GNU General Public License (GPL)
